goldenset/__init__.py
goldenset/constants.py
goldenset/goldenset.py
goldenset/utils.py
goldenset_demo-0.1.8.dist-info/METADATA
goldenset_demo-0.1.8.dist-info/WHEEL
goldenset_demo-0.1.8.dist-info/RECORD
